swoop/db/__init__.py
swoop/db/__main__.py
swoop/db/cli.py
swoop/db/py.typed
swoop/db/schema.sql
swoop/db/fixtures/base_01.sql
swoop/db/migrations/00008_new_base.up.sql
swoop.db-8.0.3.dist-info/LICENSE
swoop.db-8.0.3.dist-info/METADATA
swoop.db-8.0.3.dist-info/WHEEL
swoop.db-8.0.3.dist-info/entry_points.txt
swoop.db-8.0.3.dist-info/top_level.txt
swoop.db-8.0.3.dist-info/RECORD
